puckdns/__init__.py
puckdns/_version.py
puckdns/puckDnsParser.py
puckdns/puckdnsExceptions.py
puckdns/tests/__init__.py
puckdns/tests/test_puckAPI.py
puckdns-1.0.1.dist-info/LICENSE
puckdns-1.0.1.dist-info/METADATA
puckdns-1.0.1.dist-info/WHEEL
puckdns-1.0.1.dist-info/top_level.txt
puckdns-1.0.1.dist-info/RECORD
